gid_tasks/__init__.py
gid_tasks/__main__.py
gid_tasks/actions.py
gid_tasks/errors.py
gid_tasks/_custom_invoke_classes/__init__.py
gid_tasks/_custom_invoke_classes/custom_context.py
gid_tasks/_custom_invoke_classes/custom_programm.py
gid_tasks/_custom_invoke_classes/custom_task_objects.py
gid_tasks/hackler/__init__.py
gid_tasks/hackler/git_commander.py
gid_tasks/hackler/imports_cleaner.py
gid_tasks/hackler/workspace_cleaner.py
gid_tasks/hackler/dependencies_handling/__init__.py
gid_tasks/hackler/dependencies_handling/finder.py
gid_tasks/hackler/doc_handling/__init__.py
gid_tasks/hackler/doc_handling/todo_hackler/__init__.py
gid_tasks/hackler/doc_handling/todo_hackler/todo_collector.py
gid_tasks/hackler/doc_handling/todo_hackler/todo_templates/__init__.py
gid_tasks/hackler/doc_handling/todo_hackler/todo_templates/basic_template.jinja
gid_tasks/project_info/__init__.py
gid_tasks/project_info/main_module_item.py
gid_tasks/project_info/project.py
gid_tasks/project_info/toml.py
gid_tasks/project_info/vscode_objects.py
gid_tasks/utility/__init__.py
gid_tasks/utility/console.py
gid_tasks/utility/enums.py
gid_tasks/utility/misc.py
gid_tasks/utility/vscode_utils/__init__.py
gid_tasks/utility/vscode_utils/snippets_utils.py
gid_tasks/version_handling/__init__.py
gid_tasks/version_handling/finder.py
gid_tasks/version_handling/version_item.py
gid_tasks/vscode_classes/__init__.py
gid_tasks-0.0.2.dist-info/entry_points.txt
gid_tasks-0.0.2.dist-info/LICENSE
gid_tasks-0.0.2.dist-info/WHEEL
gid_tasks-0.0.2.dist-info/METADATA
gid_tasks-0.0.2.dist-info/RECORD
